CHANGES.md
MANIFEST.in
README.md
pytest.ini
setup.cfg
setup.py
tox.ini
elixr/__init__.py
elixr/core.py
elixr/exthook.py
elixr/utils.py
elixr.egg-info/PKG-INFO
elixr.egg-info/SOURCES.txt
elixr.egg-info/dependency_links.txt
elixr.egg-info/top_level.txt
elixr/ext/__init__.py
tests/test_core.py