Metadata-Version: 1.1
Name: elixr
Version: 0.1
Summary: A python general purpose utility library
Home-page: https://github.com/babdulhakim2/elixr.git
Author: Abdul-Hakeem Shaibu
Author-email: info@hazeltek.com
License: UNKNOWN
Download-URL: https://github.com/babdulhakim2/elixr.git
Keywords: testing,logging,example
Platform: UNKNOWN
